[
    {
        "title": "[LIVE] MEK Supporters in Paris Protest Iran Executions, Urge Participation in June 20 Rally - Iran Freedom",
        "level": "Caution",
        "date": "23:47"
    },
    {
        "title": "[LIVE] Paris after-school staff strike to denounce climate of suspicion amid abuse scandal - Le Monde.fr",
        "level": "Caution",
        "date": "23:47"
    },
    {
        "title": "[LIVE] Kim Kardashian Seeks Just $1.17 in Civil Damages Hearing Tied to Terrifying Paris Robbery - Yahoo",
        "level": "Alert",
        "date": "23:47"
    },
    {
        "title": "[LIVE] French Open players plan media protest over prize money share - ESPN",
        "level": "Caution",
        "date": "23:47"
    },
    {
        "title": "[LIVE] Kering Employees Held Strike in Italy to Protest McQueen Layoffs - WWD",
        "level": "Caution",
        "date": "23:47"
    },
    {
        "title": "[LIVE] Paris airport strike on June 18: which routes are at risk of delays? - The Connexion",
        "level": "Caution",
        "date": "23:47"
    },
    {
        "title": "[LIVE] Saying less has meaning for top-10 players in prize money protest at the French Open - Daily Herald",
        "level": "Caution",
        "date": "23:47"
    },
    {
        "title": "[LIVE] Licensable picture: FRANCE-PARIS-PROTEST-FUEL-ECONOMY - Reuters Connect",
        "level": "Caution",
        "date": "23:47"
    },
    {
        "title": "[LIVE] Paris airport staff call June strike - The Local France",
        "level": "Caution",
        "date": "23:47"
    },
    {
        "title": "[LIVE] Ground-Staff Strike Announced for 18 June at Paris-Charles de Gaulle Airport - VisaHQ",
        "level": "Caution",
        "date": "23:47"
    }
]