[
    {
        "title": "[LIVE] Paris airports ordered to cut Sunday flights as heavy snow forecast - VisaHQ",
        "level": "Caution",
        "date": "06:29"
    },
    {
        "title": "[LIVE] Teachers strike in Paris' Ile-de-France region over planned job cuts - Anadolu Ajansı",
        "level": "Caution",
        "date": "06:29"
    },
    {
        "title": "[LIVE] Savannah's violent crime, homicides rise in 2025; shootings down - Savannah Morning News",
        "level": "Caution",
        "date": "06:29"
    },
    {
        "title": "[LIVE] Decade-long ticket scam exposed at Louvre Paris - DW.com",
        "level": "Caution",
        "date": "06:29"
    },
    {
        "title": "[LIVE] Protest outside the French Foreign Ministry in Paris over diplomat's Epstein ties - Reuters Connect",
        "level": "Caution",
        "date": "06:29"
    },
    {
        "title": "[LIVE] RER C: Disrupted service expected this Thursday, February 19, due to a workers' strike - Sortir à Paris",
        "level": "Caution",
        "date": "06:29"
    },
    {
        "title": "[LIVE] Sud-Rail Calls Paris-Area Train Conductors’ Strike Over Holiday Getaway Weekend - VisaHQ",
        "level": "Caution",
        "date": "06:29"
    },
    {
        "title": "[LIVE] Transport in Île-de-France: find out about upcoming works and closures - Sortir à Paris",
        "level": "Caution",
        "date": "06:29"
    },
    {
        "title": "[LIVE] Vueling Cabin-Crew Strike in France Enters Sixth Week, Disrupting Paris-Orly Flights - VisaHQ",
        "level": "Caution",
        "date": "06:29"
    },
    {
        "title": "[LIVE] French air-traffic controllers call four-day strike for 7–10 October 2026 - VisaHQ",
        "level": "Caution",
        "date": "06:29"
    }
]